countvalues/__init__.py
countvalues/_modidx.py
countvalues/core.py
countvalues-0.0.1.dist-info/LICENSE
countvalues-0.0.1.dist-info/METADATA
countvalues-0.0.1.dist-info/WHEEL
countvalues-0.0.1.dist-info/entry_points.txt
countvalues-0.0.1.dist-info/top_level.txt
countvalues-0.0.1.dist-info/RECORD
